AesEverywhere/__init__.py
AesEverywhere/aes256.py
aes_everywhere-1.2.10.dist-info/METADATA
aes_everywhere-1.2.10.dist-info/WHEEL
aes_everywhere-1.2.10.dist-info/top_level.txt
aes_everywhere-1.2.10.dist-info/RECORD
