Metadata-Version: 2.1
Name: aes-everywhere
Version: 1.2.10
Summary: AES Everywhere - Cross Language Encryption Library
Home-page: https://github.com/mervick/aes-everywhere
Author: Andrey Izman
Author-email: izmanw@gmail.com
License: UNKNOWN
Project-URL: Bug Tracker, https://github.com/mervick/aes-everywhere/issues
Project-URL: Source Code, https://github.com/mervick/aes-everywhere
Platform: UNKNOWN
Classifier: License :: OSI Approved :: MIT License
Classifier: Operating System :: OS Independent
Classifier: Operating System :: Unix
Classifier: Operating System :: Microsoft :: Windows
Classifier: Operating System :: MacOS :: MacOS X
Classifier: Programming Language :: Python :: 2
Classifier: Programming Language :: Python :: 3
Classifier: Topic :: Security :: Cryptography
Requires-Python: >=2.7
